README.md
setup.py
py_timod.egg-info/PKG-INFO
py_timod.egg-info/SOURCES.txt
py_timod.egg-info/dependency_links.txt
py_timod.egg-info/requires.txt
py_timod.egg-info/top_level.txt
timod/__init__.py
timod/ex.py
timod/pkg.py
timod/proto.py
timod/tihandler.py
timod/util.py