Metadata-Version: 2.1
Name: py-timod
Version: 0.0.1
Summary: ThingsDB module builder
Home-page: https://github.com/thingsdb/py-timod
Author: Jeroen van der Heijden
Author-email: jeroen@transceptor.technology
License: GPLv3+
Keywords: database connector module builder
Platform: UNKNOWN
Classifier: Development Status :: 4 - Beta
Classifier: Intended Audience :: Developers
Classifier: Topic :: Software Development :: Build Tools
Classifier: License :: OSI Approved :: GNU General Public License v3 or later (GPLv3+)
Classifier: Programming Language :: Python :: 3.6
Classifier: Programming Language :: Python :: 3.7
Classifier: Programming Language :: Python :: 3.8
Classifier: Programming Language :: Python :: 3.9
